aiogram_datepicker/__init__.py
aiogram_datepicker/callback_data.py
aiogram_datepicker/custom_action.py
aiogram_datepicker/datepicker.py
aiogram_datepicker/helpers.py
aiogram_datepicker/settings.py
aiogram_datepicker/views/__init__.py
aiogram_datepicker/views/base.py
aiogram_datepicker/views/day.py
aiogram_datepicker/views/month.py
aiogram_datepicker/views/year.py
aiogram_datepicker-0.0.8.dist-info/LICENSE.txt
aiogram_datepicker-0.0.8.dist-info/METADATA
aiogram_datepicker-0.0.8.dist-info/WHEEL
aiogram_datepicker-0.0.8.dist-info/top_level.txt
aiogram_datepicker-0.0.8.dist-info/RECORD
