Metadata-Version: 2.1
Name: aiogram-datepicker
Version: 0.0.8
Summary: Telegram Bots datepicker & Aiogram datepicker
Home-page: https://github.com/netbriler/aiogram-datepicker
Author: Briler
Author-email: netbriler@gmail.com
License: MIT
Download-URL: https://github.com/netbriler/aiogram-datepicker/archive/refs/tags/0.0.8.tar.gz
Keywords: Aiogram,Telegram,Bots,Calendar,Datepicker
Platform: UNKNOWN
Classifier: Development Status :: 3 - Alpha
Classifier: Intended Audience :: Developers
Classifier: Topic :: Software Development :: Libraries :: Python Modules
Classifier: License :: OSI Approved :: MIT License
Classifier: Programming Language :: Python :: 3
Classifier: Programming Language :: Python :: 3.6
Classifier: Programming Language :: Python :: 3.7
Classifier: Programming Language :: Python :: 3.8
Classifier: Programming Language :: Python :: 3.9
Classifier: Programming Language :: Python :: 3.10
Requires-Python: >=3.9
License-File: LICENSE.txt
